commit_message_cli/__init__.py
commit_message_cli/__main__.py
commit_message_cli/cli.py
smoothdev_commit_message_cli-1.0.5.dist-info/METADATA
smoothdev_commit_message_cli-1.0.5.dist-info/WHEEL
smoothdev_commit_message_cli-1.0.5.dist-info/entry_points.txt
smoothdev_commit_message_cli-1.0.5.dist-info/RECORD
