Metadata-Version: 2.1
Name: smoothdev-commit-message-cli
Version: 1.0.5
Summary: SmoothDev AI-powered commit message generator CLI tool
Home-page: https://github.com/smoothdev-io/commit-message-cli
License: MIT
Keywords: git,commit,ai,cli,smoothdev
Author: SmoothDev Technologies Inc
Author-email: info@smoothdev.io
Requires-Python: >=3.12,<4.0
Classifier: License :: OSI Approved :: MIT License
Classifier: Programming Language :: Python :: 3
Classifier: Programming Language :: Python :: 3.12
Classifier: Programming Language :: Python :: 3.13
Requires-Dist: requests (>=2.31.0,<3.0.0)
Project-URL: Repository, https://github.com/smoothdev-io/commit-message-cli
